pytreeclass/__init__.py
pytreeclass/_src/__init__.py
pytreeclass/_src/code_build.py
pytreeclass/_src/tree_base.py
pytreeclass/_src/tree_index.py
pytreeclass/_src/tree_mask.py
pytreeclass/_src/tree_pprint.py
pytreeclass/_src/tree_util.py
pytreeclass/_src/backend/__init__.py
pytreeclass/_src/backend/arraylib/__init__.py
pytreeclass/_src/backend/arraylib/base.py
pytreeclass/_src/backend/arraylib/jax.py
pytreeclass/_src/backend/arraylib/noarray.py
pytreeclass/_src/backend/arraylib/numpy.py
pytreeclass/_src/backend/arraylib/torch.py
pytreeclass/_src/backend/treelib/__init__.py
pytreeclass/_src/backend/treelib/base.py
pytreeclass/_src/backend/treelib/jax.py
pytreeclass/_src/backend/treelib/optree.py
pytreeclass-0.11.0.dist-info/LICENSE
pytreeclass-0.11.0.dist-info/METADATA
pytreeclass-0.11.0.dist-info/WHEEL
pytreeclass-0.11.0.dist-info/top_level.txt
pytreeclass-0.11.0.dist-info/RECORD
