Metadata-Version: 2.2
Name: pytreeclass
Version: 0.11.0
Summary: Visualize, create, and operate on pytrees in the most intuitive way possible.
Author-email: Mahmoud Asem <mahmoudasem00@gmail.com>
License:                                  Apache License
Project-URL: Source, https://github.com/ASEM000/pytreeclass
Keywords: jax,neural-networks,functional-programming,machine-learning
Classifier: Development Status :: 5 - Production/Stable
Classifier: Environment :: Console
Classifier: Intended Audience :: Science/Research
Classifier: Intended Audience :: Developers
Classifier: License :: OSI Approved :: Apache Software License
Classifier: Operating System :: OS Independent
Classifier: Programming Language :: Python
Classifier: Programming Language :: Python :: 3
Classifier: Topic :: Scientific/Engineering :: Artificial Intelligence
Classifier: Topic :: Software Development :: Libraries :: Python Modules
Requires-Python: >=3.8
License-File: LICENSE
Requires-Dist: typing-extensions
Provides-Extra: default
Requires-Dist: optree; extra == "default"
Provides-Extra: jax
Requires-Dist: jax>=0.4.7; extra == "jax"
Provides-Extra: numpy
Requires-Dist: numpy; extra == "numpy"
Requires-Dist: optree; extra == "numpy"
Provides-Extra: torch
Requires-Dist: torch; extra == "torch"
Requires-Dist: optree; extra == "torch"
